os_brick/__init__.py
os_brick/constants.py
os_brick/exception.py
os_brick/executor.py
os_brick/i18n.py
os_brick/opts.py
os_brick/utils.py
os_brick/version.py
os_brick/caches/__init__.py
os_brick/caches/opencas.py
os_brick/encryptors/__init__.py
os_brick/encryptors/base.py
os_brick/encryptors/cryptsetup.py
os_brick/encryptors/luks.py
os_brick/encryptors/nop.py
os_brick/initiator/__init__.py
os_brick/initiator/connector.py
os_brick/initiator/host_driver.py
os_brick/initiator/initiator_connector.py
os_brick/initiator/linuxfc.py
os_brick/initiator/linuxrbd.py
os_brick/initiator/linuxscsi.py
os_brick/initiator/storpool_utils.py
os_brick/initiator/utils.py
os_brick/initiator/connectors/__init__.py
os_brick/initiator/connectors/base.py
os_brick/initiator/connectors/base_iscsi.py
os_brick/initiator/connectors/base_rbd.py
os_brick/initiator/connectors/fake.py
os_brick/initiator/connectors/fibre_channel.py
os_brick/initiator/connectors/fibre_channel_ppc64.py
os_brick/initiator/connectors/fibre_channel_s390x.py
os_brick/initiator/connectors/gpfs.py
os_brick/initiator/connectors/huawei.py
os_brick/initiator/connectors/iscsi.py
os_brick/initiator/connectors/lightos.py
os_brick/initiator/connectors/local.py
os_brick/initiator/connectors/nvmeof.py
os_brick/initiator/connectors/rbd.py
os_brick/initiator/connectors/remotefs.py
os_brick/initiator/connectors/scaleio.py
os_brick/initiator/connectors/storpool.py
os_brick/initiator/connectors/vmware.py
os_brick/initiator/windows/__init__.py
os_brick/initiator/windows/base.py
os_brick/initiator/windows/fibre_channel.py
os_brick/initiator/windows/iscsi.py
os_brick/initiator/windows/rbd.py
os_brick/initiator/windows/smbfs.py
os_brick/local_dev/__init__.py
os_brick/local_dev/lvm.py
os_brick/privileged/__init__.py
os_brick/privileged/lightos.py
os_brick/privileged/nvmeof.py
os_brick/privileged/rbd.py
os_brick/privileged/rootwrap.py
os_brick/privileged/scaleio.py
os_brick/remotefs/__init__.py
os_brick/remotefs/remotefs.py
os_brick-6.14.0.dist-info/licenses/AUTHORS
os_brick-6.14.0.dist-info/licenses/LICENSE
os_brick-6.14.0.dist-info/METADATA
os_brick-6.14.0.dist-info/WHEEL
os_brick-6.14.0.dist-info/entry_points.txt
os_brick-6.14.0.dist-info/pbr.json
os_brick-6.14.0.dist-info/top_level.txt
os_brick-6.14.0.dist-info/RECORD
